MANIFEST.in
README
requirements.txt
setup.py
ajenti.plugin.supervisor.egg-info/PKG-INFO
ajenti.plugin.supervisor.egg-info/SOURCES.txt
ajenti.plugin.supervisor.egg-info/dependency_links.txt
ajenti.plugin.supervisor.egg-info/requires.txt
ajenti.plugin.supervisor.egg-info/top_level.txt
ajenti_plugin_supervisor/__init__.py
ajenti_plugin_supervisor/api.py
ajenti_plugin_supervisor/aug.py
ajenti_plugin_supervisor/main.py
ajenti_plugin_supervisor/plugin.yml
ajenti_plugin_supervisor/requirements.txt
ajenti_plugin_supervisor/supervisor.aug
ajenti_plugin_supervisor/locale/app.pot
ajenti_plugin_supervisor/locale/af/LC_MESSAGES/app.js
ajenti_plugin_supervisor/locale/af/LC_MESSAGES/app.po
ajenti_plugin_supervisor/locale/af/LC_MESSAGES/app.po~
ajenti_plugin_supervisor/locale/ar/LC_MESSAGES/app.js
ajenti_plugin_supervisor/locale/ar/LC_MESSAGES/app.po
ajenti_plugin_supervisor/locale/ar/LC_MESSAGES/app.po~
ajenti_plugin_supervisor/locale/be/LC_MESSAGES/app.js
ajenti_plugin_supervisor/locale/be/LC_MESSAGES/app.po
ajenti_plugin_supervisor/locale/be/LC_MESSAGES/app.po~
ajenti_plugin_supervisor/locale/bg/LC_MESSAGES/app.js
ajenti_plugin_supervisor/locale/bg/LC_MESSAGES/app.po
ajenti_plugin_supervisor/locale/bg/LC_MESSAGES/app.po~
ajenti_plugin_supervisor/locale/bn/LC_MESSAGES/app.js
ajenti_plugin_supervisor/locale/bn/LC_MESSAGES/app.po
ajenti_plugin_supervisor/locale/bn/LC_MESSAGES/app.po~
ajenti_plugin_supervisor/locale/bs/LC_MESSAGES/app.js
ajenti_plugin_supervisor/locale/bs/LC_MESSAGES/app.po
ajenti_plugin_supervisor/locale/ca/LC_MESSAGES/app.js
ajenti_plugin_supervisor/locale/ca/LC_MESSAGES/app.po
ajenti_plugin_supervisor/locale/ca/LC_MESSAGES/app.po~
ajenti_plugin_supervisor/locale/cs/LC_MESSAGES/app.js
ajenti_plugin_supervisor/locale/cs/LC_MESSAGES/app.po
ajenti_plugin_supervisor/locale/cs/LC_MESSAGES/app.po~
ajenti_plugin_supervisor/locale/da/LC_MESSAGES/app.js
ajenti_plugin_supervisor/locale/da/LC_MESSAGES/app.po
ajenti_plugin_supervisor/locale/da/LC_MESSAGES/app.po~
ajenti_plugin_supervisor/locale/de/LC_MESSAGES/app.js
ajenti_plugin_supervisor/locale/de/LC_MESSAGES/app.po
ajenti_plugin_supervisor/locale/de/LC_MESSAGES/app.po~
ajenti_plugin_supervisor/locale/el/LC_MESSAGES/app.js
