Metadata-Version: 1.2
Name: ajenti.plugin.supervisor
Version: 0.20
Summary: Supervisor
Home-page: https://ajenti.org
Author: Ajenti project
Author-email: e@ajenti.org
License: UNKNOWN
Platform: UNKNOWN
Requires-Python: >=3
